bcedit_madeby_train/__init__.py
bcedit_madeby_train/__main__.py
bcedit_madeby_train/adb_handler.py
bcedit_madeby_train/config_manager.py
bcedit_madeby_train/csv_handler.py
bcedit_madeby_train/feature_handler.py
bcedit_madeby_train/game_data_getter.py
bcedit_madeby_train/helper.py
bcedit_madeby_train/item.py
bcedit_madeby_train/locale_handler.py
bcedit_madeby_train/managed_item.py
bcedit_madeby_train/parse_save.py
bcedit_madeby_train/patcher.py
bcedit_madeby_train/root_handler.py
bcedit_madeby_train/serialise_save.py
bcedit_madeby_train/server_handler.py
bcedit_madeby_train/tracker.py
bcedit_madeby_train/updater.py
bcedit_madeby_train/user_input_handler.py
bcedit_madeby_train/edits/__init__.py
bcedit_madeby_train/edits/basic/__init__.py
bcedit_madeby_train/edits/basic/basic_items.py
bcedit_madeby_train/edits/basic/catfruit.py
bcedit_madeby_train/edits/basic/catseyes.py
bcedit_madeby_train/edits/basic/ototo_base_mats.py
bcedit_madeby_train/edits/basic/talent_orbs.py
bcedit_madeby_train/edits/basic/talent_orbs_new.py
bcedit_madeby_train/edits/cats/__init__.py
bcedit_madeby_train/edits/cats/cat_helper.py
bcedit_madeby_train/edits/cats/cat_id_selector.py
bcedit_madeby_train/edits/cats/chara_drop.py
bcedit_madeby_train/edits/cats/clear_cat_guide.py
bcedit_madeby_train/edits/cats/evolve_cats.py
bcedit_madeby_train/edits/cats/get_remove_cats.py
bcedit_madeby_train/edits/cats/talents.py
bcedit_madeby_train/edits/cats/upgrade_blue.py
bcedit_madeby_train/edits/cats/upgrade_cats.py
bcedit_madeby_train/edits/gamototo/__init__.py
bcedit_madeby_train/edits/gamototo/fix_gamatoto.py
bcedit_madeby_train/edits/gamototo/gamatoto_xp.py
bcedit_madeby_train/edits/gamototo/helpers.py
bcedit_madeby_train/edits/gamototo/ototo_cat_cannon.py
bcedit_madeby_train/edits/levels/__init__.py
bcedit_madeby_train/edits/levels/aku.py
bcedit_madeby_train/edits/levels/allow_filibuster_clearing.py
bcedit_madeby_train/edits/levels/behemoth_culling.py
bcedit_madeby_train/edits/levels/clear_tutorial.py
bcedit_madeby_train-1.0.dist-info/METADATA
bcedit_madeby_train-1.0.dist-info/WHEEL
bcedit_madeby_train-1.0.dist-info/top_level.txt
bcedit_madeby_train-1.0.dist-info/RECORD
